CHANGES.rst
MANIFEST.in
README.rst
setup.py
plone/__init__.py
plone.app.jquery.egg-info/PKG-INFO
plone.app.jquery.egg-info/SOURCES.txt
plone.app.jquery.egg-info/dependency_links.txt
plone.app.jquery.egg-info/entry_points.txt
plone.app.jquery.egg-info/namespace_packages.txt
plone.app.jquery.egg-info/not-zip-safe
plone.app.jquery.egg-info/requires.txt
plone.app.jquery.egg-info/top_level.txt
plone/app/__init__.py
plone/app/jquery/__init__.py
plone/app/jquery/configure.zcml
plone/app/jquery/jquery-1.11.2.js
plone/app/jquery/jquery-1.11.2.min.js
plone/app/jquery/jquery-migrate-1.2.1.js
plone/app/jquery/jquery-migrate-1.2.1.min.js
plone/app/jquery/jquery.min.map
plone/app/jquery/rpl-minmap.sh
plone/app/jquery/upgrades.py
plone/app/jquery/upgrades.zcml
plone/app/jquery/profiles/default/jsregistry.xml
plone/app/jquery/profiles/default/metadata.xml
plone/app/jquery/profiles/development/jsregistry.xml
plone/app/jquery/profiles/development/metadata.xml
plone/app/jquery/profiles/initial-upgrade/jsregistry.xml